pythreatgrid2/__init__.py
pythreatgrid2/api.py
pythreatgrid2-0.1.1.dist-info/LICENSE
pythreatgrid2-0.1.1.dist-info/METADATA
pythreatgrid2-0.1.1.dist-info/WHEEL
pythreatgrid2-0.1.1.dist-info/top_level.txt
pythreatgrid2-0.1.1.dist-info/RECORD
