Metadata-Version: 2.1
Name: pythreatgrid2
Version: 0.1.1
Summary: Python wrapper around the Threat Grid API
Home-page: https://github.com/Te-k/pythreatgrid
Author: Tek
Author-email: tek@randhome.io
License: MIT
Keywords: security
Platform: UNKNOWN
Classifier: Programming Language :: Python :: 3
Classifier: License :: OSI Approved :: MIT License
Classifier: Operating System :: OS Independent
Requires-Python: >=3.5
Requires-Dist: requests
